dashai_test_classification_metrics_plugin/__init__.py
dashai_test_classification_metrics_plugin/accuracy.py
dashai_test_classification_metrics_plugin/classification_metric.py
dashai_test_classification_metrics_plugin/f1.py
dashai_test_classification_metrics_plugin/precision.py
dashai_test_classification_metrics_plugin/recall.py
dashai_test_classification_metrics_plugin-0.0.3.dist-info/METADATA
dashai_test_classification_metrics_plugin-0.0.3.dist-info/WHEEL
dashai_test_classification_metrics_plugin-0.0.3.dist-info/entry_points.txt
dashai_test_classification_metrics_plugin-0.0.3.dist-info/RECORD
