Metadata-Version: 2.3
Name: dashai_test_classification_metrics_plugin
Version: 0.0.3
Summary: Classification Metrics Plugin for DashAI
Project-URL: Homepage, https://github.com/DashAISoftware/DashAI
Project-URL: Issues, https://github.com/DashAISoftware/DashAI/issues
Author: DashAI team
Author-email: dashaisoftware@gmail.com
Keywords: DashAI,Metric
Requires-Python: >=3.8
